html_index/.gitignore
html_index/__init__.py
html_index/index.py
html_index/assets/README.md
html_index/assets/__file_template.html
html_index/assets/__index_template.html
html_index/assets/__init__.py
html_index/assets/__url_template.html
html_index/assets/generate_icon.py
html_index/assets/icons.yml
html_index/assets/__icons/actionscript.svg
html_index/assets/__icons/ai.svg
html_index/assets/__icons/android.svg
html_index/assets/__icons/angular-component.svg
html_index/assets/__icons/angular-directive.svg
html_index/assets/__icons/angular-guard.svg
html_index/assets/__icons/angular-pipe.svg
html_index/assets/__icons/angular-resolver.svg
html_index/assets/__icons/angular-routing.svg
html_index/assets/__icons/angular-service.svg
html_index/assets/__icons/angular.svg
html_index/assets/__icons/applescript.svg
html_index/assets/__icons/arduino.svg
html_index/assets/__icons/assembly.svg
html_index/assets/__icons/audio.svg
html_index/assets/__icons/autohotkey.svg
html_index/assets/__icons/babel.svg
html_index/assets/__icons/blade.svg
html_index/assets/__icons/bower.svg
html_index/assets/__icons/browserlist.svg
html_index/assets/__icons/c.svg
html_index/assets/__icons/cabal.svg
html_index/assets/__icons/cargo-lock.svg
html_index/assets/__icons/certificate.svg
html_index/assets/__icons/changelog.svg
html_index/assets/__icons/clojure.svg
html_index/assets/__icons/cmake.svg
html_index/assets/__icons/cmd.svg
html_index/assets/__icons/coffee.svg
html_index/assets/__icons/coldfusion.svg
html_index/assets/__icons/conduct.svg
html_index/assets/__icons/console.svg
html_index/assets/__icons/contributing.svg
html_index/assets/__icons/cpp.svg
html_index/assets/__icons/credits.svg
html_index/assets/__icons/csharp.svg
html_index/assets/__icons/css-map.svg
html_index/assets/__icons/css.svg
html_index/assets/__icons/dart.svg
html_index/assets/__icons/database.svg
html_index/assets/__icons/dlang.svg
html_index/assets/__icons/docker.svg
html_index/assets/__icons/document.svg
html_index-1.0.9.dist-info/LICENSE
html_index-1.0.9.dist-info/METADATA
html_index-1.0.9.dist-info/WHEEL
html_index-1.0.9.dist-info/entry_points.txt
html_index-1.0.9.dist-info/top_level.txt
html_index-1.0.9.dist-info/RECORD
