Metadata-Version: 2.1
Name: html-index
Version: 1.0.9
Summary: HTML file indexing generator.
Home-page: https://github.com/Mg138/html-index
Author: Madeline Sparkle
Author-email: muguang138@gmail.com
License: UNKNOWN
Platform: UNKNOWN
Classifier: Programming Language :: Python :: 3
Classifier: License :: OSI Approved :: MIT License
Classifier: Operating System :: OS Independent
Requires-Python: >=3.6
License-File: LICENSE
Requires-Dist: PyYAML (~=5.4.1)
